features/__init__.py
features/environment.py
features/steps/__init__.py
features/steps/analysis.py
features/steps/descriptor_CLI_interfaces.py
features/steps/descriptors.py
features/steps/graph.py
features/steps/inputoutput.py
features/steps/manipulation.py
features/steps/math.py
features/steps/matrix_helper.py
features/steps/normalization.py
lib/__init__.py
lib/analysis.py
lib/descriptor_CLI_interfaces.py
lib/descriptors.py
lib/graph.py
lib/inputoutput.py
lib/main_script_helper_functions.py
lib/manipulation.py
lib/mathematics.py
lib/matrix_to_many_matrix.py
lib/normalization.py
lib/outputcolorer.py
lib/supervised_bak.py
lib/supervised_learning.py
lib/textclustering.py
lib/unsupervised_learning.py
test/__init__.py
test/test_analysis.py
test/test_descriptors.py
test/test_inputfastatests.py
test/test_manipulation.py
test/test_slicing.py
vectools-0.1.3.2.50.data/scripts/vectools
vectoolslib/__init__.py
vectoolslib/analysis.py
vectoolslib/descriptor_CLI_interfaces.py
vectoolslib/descriptors.py
vectoolslib/error_handling.py
vectoolslib/graph.py
vectoolslib/inputoutput.py
vectoolslib/main_script_helper_functions.py
vectoolslib/mainhelp.py
vectoolslib/manipulation.py
vectoolslib/mathematics.py
vectoolslib/matrix_to_many_matrix.py
vectoolslib/normalization.py
vectoolslib/outputcolorer.py
vectoolslib/supervised_bak.py
vectoolslib/supervised_learning.py
vectoolslib/textclustering.py
vectoolslib/unsupervised_learning.py
vectoolslib/utilities.py
vectoolslib/vectools_docstring.py
vectools-0.1.3.2.50.dist-info/LICENSE
vectools-0.1.3.2.50.dist-info/LICENSE.txt
vectools-0.1.3.2.50.dist-info/METADATA
vectools-0.1.3.2.50.dist-info/WHEEL
vectools-0.1.3.2.50.dist-info/top_level.txt
vectools-0.1.3.2.50.dist-info/RECORD
