Metadata-Version: 2.1
Name: vectools
Version: 0.1.3.2.50
Summary: Vectools - A bioinformatics-focused command-line utility for linear algebra,         table manipulation, machine leaning, networks/graphs, and more.
Home-page: UNKNOWN
Author: Tyler Weirick
Author-email: tyler.weirick@gmail.com
License: MIT
Platform: any
Requires-Dist: numpy (>=1.9.2)
Requires-Dist: scipy (>=0.16.0)
Requires-Dist: scikit-learn (>=0.16.1)
Requires-Dist: networkx (>=1.11)
Requires-Dist: pandas (>=0.19.0)
Requires-Dist: natsort (>=5.0.2behave)
Requires-Dist: mock
